CodeConvert/__init__.py
CodeConvert/convert.py
CodeConvert-3.0.2.dist-info/METADATA
CodeConvert-3.0.2.dist-info/WHEEL
CodeConvert-3.0.2.dist-info/top_level.txt
CodeConvert-3.0.2.dist-info/RECORD
