Metadata-Version: 1.1
Name: CodeConvert
Version: 3.0.2
Summary: Code Convert for Python 2.x for Humans™
Home-page: https://github.com/Brightcells/CodeConvert
Author: Hackathon
Author-email: kimi.huang@brightcells.com
License: UNKNOWN
Keywords: CodeConvert unicode utf8 utf-8 gbk latin1 raw_unicode_escape
Platform: UNKNOWN
Classifier: License :: OSI Approved :: BSD License
Classifier: Programming Language :: Python
Classifier: Programming Language :: Python :: 2
Classifier: Programming Language :: Python :: 2.5
Classifier: Programming Language :: Python :: 2.6
Classifier: Programming Language :: Python :: 2.7
Classifier: Topic :: Software Development :: Libraries :: Python Modules
